simplesocks/__init.py
simplesocks/client.py
simplesocks/server.py
simplesocks-1.0.0.dist-info/LICENSE
simplesocks-1.0.0.dist-info/METADATA
simplesocks-1.0.0.dist-info/WHEEL
simplesocks-1.0.0.dist-info/top_level.txt
simplesocks-1.0.0.dist-info/RECORD
