Metadata-Version: 2.1
Name: simplesocks
Version: 1.0.0
Summary: A simple wrapper written on top of standard python sockets
Author-email: Dulsara Dhanuka <dulsara.dhanuka@gmail.com>
Project-URL: Homepage, https://github.com/DulsaraDhanuka/simplesocks
Project-URL: Bug Tracker, https://github.com/DulsaraDhanuka/simplesocks/issues
Classifier: Programming Language :: Python :: 3
Classifier: License :: OSI Approved :: MIT License
Classifier: Operating System :: OS Independent
Requires-Python: >=3.7
License-File: LICENSE
Requires-Dist: cryptography
